carpenter_py/__init__.py
carpenter_py/cli.py
carpenter_py/env.py
carpenter_py/server.py
carpenter_py/settings.py
carpenter_py/actions/__init__.py
carpenter_py/middleware/__init__.py
carpenter_py/middleware/authorization.py
carpenter_py/utils/__init__.py
carpenter_py/utils/generate_ts_types.py
carpenter_py/utils/log.py
carpenter_py/utils/page_mapper.py
carpenter_py-0.1.1.dist-info/licenses/LICENSE
scripts/__init__.py
scripts/build.py
scripts/dev.py
scripts/scaffold_app.py
carpenter_py-0.1.1.dist-info/METADATA
carpenter_py-0.1.1.dist-info/WHEEL
carpenter_py-0.1.1.dist-info/entry_points.txt
carpenter_py-0.1.1.dist-info/top_level.txt
carpenter_py-0.1.1.dist-info/RECORD
