Metadata-Version: 2.4
Name: carpenter-py
Version: 0.1.1
Summary: Core runtime for executing and managing actions in Carpenter ecosystem.
Author: Eric Kweyunga
Author-email: Eric Kweyunga <maverickweyunga@gmail.com>
License: MIT
Classifier: Programming Language :: Python :: 3
Classifier: License :: OSI Approved :: MIT License
Classifier: Operating System :: OS Independent
Requires-Python: >=3.8
License-File: LICENSE
Requires-Dist: altgraph==0.17.4
Requires-Dist: annotated-types==0.7.0
Requires-Dist: anyio==4.9.0
Requires-Dist: build==1.2.2.post1
Requires-Dist: certifi==2025.1.31
Requires-Dist: charset-normalizer==3.4.1
Requires-Dist: click==8.1.8
Requires-Dist: colorama==0.4.6
Requires-Dist: docutils==0.21.2
Requires-Dist: h11==0.14.0
Requires-Dist: id==1.5.0
Requires-Dist: idna==3.10
Requires-Dist: jaraco.classes==3.4.0
Requires-Dist: jaraco.context==6.0.1
Requires-Dist: jaraco.functools==4.1.0
Requires-Dist: keyring==25.6.0
Requires-Dist: markdown-it-py==3.0.0
Requires-Dist: mdurl==0.1.2
Requires-Dist: more-itertools==10.6.0
Requires-Dist: nh3==0.2.21
Requires-Dist: packaging==24.2
Requires-Dist: pefile==2023.2.7
Requires-Dist: pydantic==2.11.3
Requires-Dist: pydantic-settings==2.8.1
Requires-Dist: pydantic_core==2.33.1
Requires-Dist: Pygments==2.19.1
Requires-Dist: pyinstaller==6.12.0
Requires-Dist: pyinstaller-hooks-contrib==2025.2
Requires-Dist: pyproject_hooks==1.2.0
Requires-Dist: python-dotenv==1.1.0
Requires-Dist: pywin32-ctypes==0.2.3
Requires-Dist: readme_renderer==44.0
Requires-Dist: requests==2.32.3
Requires-Dist: requests-toolbelt==1.0.0
Requires-Dist: rfc3986==2.0.0
Requires-Dist: rich==14.0.0
Requires-Dist: setuptools==78.1.0
Requires-Dist: sniffio==1.3.1
Requires-Dist: starlette==0.46.1
Requires-Dist: twine==6.1.0
Requires-Dist: typing-inspection==0.4.0
Requires-Dist: typing_extensions==4.13.2
Requires-Dist: urllib3==2.4.0
Requires-Dist: uvicorn==0.34.0
Dynamic: license-file
